testkeeper/.idea/.gitignore
testkeeper/.idea/inspectionProfiles/Project_Default.xml
testkeeper/.idea/inspectionProfiles/profiles_settings.xml
testkeeper/.idea/misc.xml
testkeeper/.idea/modules.xml
testkeeper/.idea/testkeeper.iml
testkeeper/.idea/workspace.xml
testkeeper/__init__.py
testkeeper/app.py
testkeeper/builtin/__init__.py
testkeeper/builtin/auto_load_cmd_argv.py
testkeeper/builtin/testkeeper_conf.py
testkeeper/client.py
testkeeper/db/testkeeper.db
testkeeper/exception/__init__.py
testkeeper/exception/exception.py
testkeeper/main.py
testkeeper/mock/__init__.py
testkeeper/mock/mock.py
testkeeper/module/__init__.py
testkeeper/module/execute_status_module.py
testkeeper/module/sqlite_module.py
testkeeper/service/__init__.py
testkeeper/service/job_service.py
testkeeper/service/plan_service.py
testkeeper/service/sql_interface.py
testkeeper/testkeeper_cmd_conf.yml
testkeeper/testkeeper_conf.yml
testkeeper/tkdecorator.py
testkeeper/util/__init__.py
testkeeper/util/file_operation.py
testkeeper/util/logger_operation.py
testkeeper/util/shell_utils.py
testkeeper/util/sqlalchemy_db_operation.py
testkeeper/util/system_info.py
testkeeper-0.1.0.dist-info/entry_points.txt
testkeeper-0.1.0.dist-info/LICENSE
testkeeper-0.1.0.dist-info/WHEEL
testkeeper-0.1.0.dist-info/METADATA
testkeeper-0.1.0.dist-info/RECORD
