Metadata-Version: 2.1
Name: testkeeper
Version: 0.1.0
Summary: 用于调度测试任务，观测任务执行进度
Author: 成都-阿木木
Author-email: 848257135@qq.com
Requires-Python: >=3.8,<4.0
Classifier: Programming Language :: Python :: 3
Classifier: Programming Language :: Python :: 3.8
Classifier: Programming Language :: Python :: 3.9
Requires-Dist: ddt (>=1.6.0,<2.0.0)
Requires-Dist: flask (>=2.2.2,<3.0.0)
Requires-Dist: loguru (>=0.6.0,<0.7.0)
Requires-Dist: psutil (>=5.9.4,<6.0.0)
Requires-Dist: pyyaml (>=6.0,<7.0)
Requires-Dist: requests (>=2.28.1,<3.0.0)
Requires-Dist: sqlalchemy (>=1.4.43,<2.0.0)
